{
    "functions": [
        {
            "function": "set_count",
            "count": {
                "type": "score",
                "target": "this",
                "score": "jkpof.item.count"
            }
        }
    ],
    "pools": [
        {
            "rolls": 1,
            "entries": [
                {
                    "weight": 1087,
                    "type": "tag",
                    "expand": true,
                    "name": "jkpof:give/common"
                },
                {
                    "weight": 60,
                    "type": "tag",
                    "expand": true,
                    "name": "jkpof:give/copper_made"
                },
                {
                    "weight": 1,
                    "type": "tag",
                    "expand": true,
                    "name": "jkpof:give/coral"
                },
                {
                    "weight": 1,
                    "type": "tag",
                    "expand": true,
                    "name": "jkpof:give/pottery_sherd"
                },
                {
                    "weight": 1,
                    "type": "tag",
                    "expand": true,
                    "name": "jkpof:give/smithing_template"
                },
                {
                    "weight": 1,
                    "type": "tag",
                    "expand": true,
                    "name": "bundles"
                },
                {
                    "weight": 93,
                    "type": "loot_table",
                    "value": "jkpof:item/64/common"
                },
                {
                    "weight": 1,
                    "type": "loot_table",
                    "value": "jkpof:item/arrow"
                },
                {
                    "weight": 1,
                    "type": "item",
                    "name": "bat_spawn_egg",
                    "functions": [
                        {
                            "function": "set_components",
                            "components": {
                                "item_model": "bat_spawn_egg"
                            }
                        }
                    ]
                },
                {
                    "weight": 1,
                    "type": "item",
                    "name": "ender_dragon_spawn_egg",
                    "functions": [
                        {
                            "function": "set_components",
                            "components": {
                                "entity_data": {
                                    "id": "ender_dragon",
                                    "DragonPhase": 8
                                }
                            }
                        }
                    ]
                },
                {
                    "weight": 1,
                    "type": "item",
                    "name": "creeper_spawn_egg",
                    "functions": [
                        {
                            "function": "set_components",
                            "components": {
                                "entity_data": {
                                    "id": "creeper",
                                    "ignited": true
                                }
                            }
                        },
                        {
                            "function": "set_name",
                            "entity": "this",
                            "name": [
                                {
                                    "storage": "jk:pof",
                                    "interpret": true,
                                    "nbt": "txt.lobby.item.global.self_igniting",
                                    "color": "red",
                                    "italic": false
                                },
                                {
                                    "translate": "entity.minecraft.creeper",
                                    "color": "white"
                                }
                            ]
                        }
                    ]
                }
            ]
        }
    ]
}